ru_accent_poet/__init__.py
ru_accent_poet/accent.dic
ru_accent_poet/accent1.dic
ru_accent_poet/neuro.py
ru_accent_poet/ru_accent.py
ru_accent_poet/rules.py
ru_accent_poet-0.1.5.dist-info/LICENSE
ru_accent_poet-0.1.5.dist-info/METADATA
ru_accent_poet-0.1.5.dist-info/WHEEL
ru_accent_poet-0.1.5.dist-info/top_level.txt
ru_accent_poet-0.1.5.dist-info/RECORD
