Metadata-Version: 2.1
Name: ru-accent-poet
Version: 0.1.5
Summary: A package for putting stress marks in russian poetic texts
Home-page: https://github.com/yuliya1324/ru_accent
Author: Julia Korotkova
Author-email: koylenka15@gmail.com
License: UNKNOWN
Platform: UNKNOWN
Classifier: Programming Language :: Python :: 3.8
Classifier: License :: OSI Approved :: MIT License
Classifier: Operating System :: OS Independent
Requires-Python: >=3.6
Requires-Dist: requests (>=2.21.0)
Requires-Dist: russtress
